Project/__init__.py
Project/drawable.py
Project/games.py
Project/object.py
Project/project.py
Project/project_image.jpg
Project/sound.py
Project/standard.py
progf-0.0.5.dist-info/METADATA
progf-0.0.5.dist-info/WHEEL
progf-0.0.5.dist-info/top_level.txt
progf-0.0.5.dist-info/RECORD
